hdx/freshness/dbactions/__init__.py
hdx/freshness/dbactions/__main__.py
hdx/freshness/dbactions/_version.py
hdx/freshness/dbactions/dbclean.py
hdx/freshness/dbactions/dbclone.py
hdx_data_freshness_dbclean-1.0.2.dist-info/LICENSE
hdx_data_freshness_dbclean-1.0.2.dist-info/METADATA
hdx_data_freshness_dbclean-1.0.2.dist-info/WHEEL
hdx_data_freshness_dbclean-1.0.2.dist-info/top_level.txt
hdx_data_freshness_dbclean-1.0.2.dist-info/zip-safe
hdx_data_freshness_dbclean-1.0.2.dist-info/RECORD
